LICENSE
MANIFEST.in
README.rst
setup.py
solutions/__about__.py
solutions/__init__.py
solutions.egg-info/PKG-INFO
solutions.egg-info/SOURCES.txt
solutions.egg-info/dependency_links.txt
solutions.egg-info/top_level.txt